{
  "participantID": "f016b9fd-1799-4b3b-a8a4-8b4f0dd87e26",
  "demographicsAnswers": [
    {
      "participantID": "f016b9fd-1799-4b3b-a8a4-8b4f0dd87e26",
      "age": 58,
      "gender": "female",
      "experience": "no-experience",
      "englishLevel": "beginner"
    }
  ],
  "score": 9,
  "questionData": {
    "question0": {
      "questionIndex": 0,
      "questionOrder": 1,
      "questionText": "wording change",
      "caseFormat": "camel4",
      "optionsGiven": [
        "wordingChange",
        "wardingChange",
        "wordingChagne",
        "wordingChane"
      ],
      "correctAnswerIndex": 0,
      "selectedOption": "wardingChange",
      "isCorrect": false,
      "timeTaken": 48251.5
    },
    "question1": {
      "questionIndex": 1,
      "questionOrder": 2,
      "questionText": "query indexes",
      "caseFormat": "kebab3",
      "optionsGiven": [
        "querry-indexes",
        "query-inbexes",
        "quary-indexes",
        "query-indexes"
      ],
      "correctAnswerIndex": 3,
      "selectedOption": "query-indexes",
      "isCorrect": true,
      "timeTaken": 8182.600000000035
    },
    "question2": {
      "questionIndex": 2,
      "questionOrder": 3,
      "questionText": "jump left",
      "caseFormat": "camel1",
      "optionsGiven": [
        "jumpLelt",
        "jumpLeft",
        "jumnpLeft",
        "junpLeft"
      ],
      "correctAnswerIndex": 1,
      "selectedOption": "jumpLeft",
      "isCorrect": true,
      "timeTaken": 7248.900000000023
    },
    "question3": {
      "questionIndex": 3,
      "questionOrder": 4,
      "questionText": "algorithm numbers",
      "caseFormat": "camel2",
      "optionsGiven": [
        "algorithmNumbers",
        "algorithmNunbers",
        "algorithmnNumbers",
        "algortithmNumbers"
      ],
      "correctAnswerIndex": 0,
      "selectedOption": "algorithmNumbers",
      "isCorrect": true,
      "timeTaken": 29147.20000000001
    },
    "question4": {
      "questionIndex": 4,
      "questionOrder": 5,
      "questionText": "packet size",
      "caseFormat": "camel5",
      "optionsGiven": [
        "packetsSize",
        "packetSize",
        "paketSize",
        "packetSide"
      ],
      "correctAnswerIndex": 1,
      "selectedOption": "packetSize",
      "isCorrect": true,
      "timeTaken": 11786.899999999965
    },
    "question5": {
      "questionIndex": 5,
      "questionOrder": 6,
      "questionText": "packet size",
      "caseFormat": "kebab5",
      "optionsGiven": [
        "packet-size",
        "packet-side",
        "packets-size",
        "paket-Size"
      ],
      "correctAnswerIndex": 0,
      "selectedOption": "packet-size",
      "isCorrect": true,
      "timeTaken": 11522.699999999953
    },
    "question6": {
      "questionIndex": 6,
      "questionOrder": 7,
      "questionText": "query indexes",
      "caseFormat": "camel3",
      "optionsGiven": [
        "queryIndexes",
        "queryInbexes",
        "quaryIndexes",
        "querryIndexes"
      ],
      "correctAnswerIndex": 0,
      "selectedOption": "queryIndexes",
      "isCorrect": true,
      "timeTaken": 13586.299999999988
    },
    "question7": {
      "questionIndex": 7,
      "questionOrder": 8,
      "questionText": "algorithm numbers",
      "caseFormat": "kebab2",
      "optionsGiven": [
        "algorithm-nunbers",
        "algorithm-numbers",
        "algortithm-numbers",
        "algorithmn-numbers"
      ],
      "correctAnswerIndex": 1,
      "selectedOption": "algorithm-numbers",
      "isCorrect": true,
      "timeTaken": 13175.299999999988
    },
    "question8": {
      "questionIndex": 8,
      "questionOrder": 9,
      "questionText": "wording change",
      "caseFormat": "kebab4",
      "optionsGiven": [
        "wording-change",
        "wording-chagne",
        "wording-chane",
        "warding-change"
      ],
      "correctAnswerIndex": 0,
      "selectedOption": "wording-change",
      "isCorrect": true,
      "timeTaken": 15760.300000000047
    },
    "question9": {
      "questionIndex": 9,
      "questionOrder": 10,
      "questionText": "jump left",
      "caseFormat": "kebab1",
      "optionsGiven": [
        "jump-left",
        "junp-left",
        "jump-lelt",
        "junmp-left"
      ],
      "correctAnswerIndex": 0,
      "selectedOption": "jump-left",
      "isCorrect": true,
      "timeTaken": 7056.099999999977
    }
  }
}
